Pypeline/__init__.py
Pypeline/profile.py
Pypeline/utils.py
Pypeline/Pypes/AVLTree.py
Pypeline/Pypes/BinarySearchTree.py
Pypeline/Pypes/DoublyLinkedList.py
Pypeline/Pypes/Heap.py
Pypeline/Pypes/LinkedList.py
Pypeline/Pypes/MaxHeap.py
Pypeline/Pypes/MinHeap.py
Pypeline/Pypes/Node.py
Pypeline/Pypes/Queue.py
Pypeline/Pypes/RedBlackBST.py
Pypeline/Pypes/Stack.py
Pypeline/Pypes/TernarySearchTree.py
Pypeline/Pypes/Trie.py
Pypeline/Pypes/__init__.py
python_pypeline-1.0.1.dist-info/LICENSE
python_pypeline-1.0.1.dist-info/METADATA
python_pypeline-1.0.1.dist-info/WHEEL
python_pypeline-1.0.1.dist-info/top_level.txt
python_pypeline-1.0.1.dist-info/RECORD
